{"frozen":{"name":"libestr","shortDescription":"Some essentials for string handling","versionString":"0.1.11","homepage":"http://libestr.adiscon.com/","license":{"fullName":"GNU Library General Public License v2.1 only","shortName":"lgpl21","spdxId":"LGPL-2.1-only","url":"http://spdx.org/licenses/LGPL-2.1-only.html"},"versionNumberList":[0,1,11]},"flexible":{"sources":[{"git":"https://github.com/NixOS/nixpkgs.git","commit":"22091c912a38f2f9f8cb8efd612915a9346e57cb","attributePath":["libestr"],"position":"/nix/store/z9pm444cj6kmm2m01vf28xa94bakm7cm-22091c912a38f2f9f8cb8efd612915a9346e57cb.tar.gz/pkgs/development/libraries/libestr/default.nix:13","date":"2019-03-01"}],"platforms":[{}]}}