{"frozen":{"name":"dnscrypt-wrapper","shortDescription":"A tool for adding dnscrypt support to any name resolver","versionString":"0.4.2","homepage":"https://dnscrypt.info/","license":{"fullName":"ISC License","shortName":"isc","spdxId":"ISC","url":"http://spdx.org/licenses/ISC.html"},"versionNumberList":[0,4,2]},"flexible":{"sources":[{"git":"https://github.com/NixOS/nixpkgs.git","commit":"22091c912a38f2f9f8cb8efd612915a9346e57cb","attributePath":["dnscrypt-wrapper"],"position":"/nix/store/z9pm444cj6kmm2m01vf28xa94bakm7cm-22091c912a38f2f9f8cb8efd612915a9346e57cb.tar.gz/pkgs/tools/networking/dnscrypt-wrapper/default.nix:20","date":"2019-03-01"}],"platforms":[{"kernel":{"_type":"kernel","execFormat":{"_type":"exec-format","name":"elf"},"families":{},"name":"linux"}}]}}