{"frozen":{"name":"git-cola","shortDescription":"A sleek and powerful Git GUI","versionString":"3.3","homepage":"https://github.com/git-cola/git-cola","license":{"fullName":"GNU General Public License v2.0 only","shortName":"gpl2","spdxId":"GPL-2.0-only","url":"http://spdx.org/licenses/GPL-2.0-only.html"},"versionNumberList":[3,3]},"flexible":{"sources":[{"git":"https://github.com/NixOS/nixpkgs.git","commit":"22091c912a38f2f9f8cb8efd612915a9346e57cb","attributePath":["git-cola"],"position":"/nix/store/z9pm444cj6kmm2m01vf28xa94bakm7cm-22091c912a38f2f9f8cb8efd612915a9346e57cb.tar.gz/pkgs/applications/version-management/git-and-tools/git-cola/default.nix:24","date":"2019-03-01"}],"platforms":[{"kernel":{"_type":"kernel","execFormat":{"_type":"exec-format","name":"elf"},"families":{},"name":"linux"}}]}}