{"frozen":{"name":"saw-tools","shortDescription":"Tools for software verification and analysis","versionString":"0.1-20150609","homepage":"https://saw.galois.com","license":{"free":false,"fullName":"Unfree redistributable","shortName":"unfreeRedistributable"},"versionNumberList":[0,1,"-20150609"]},"flexible":{"sources":[{"git":"https://github.com/NixOS/nixpkgs.git","commit":"6542c344bcf0077e7530a0e8f02034aa92b52b39","attributePath":["saw-tools"],"position":"/nix/store/f9gnvpp942xsz6y4wk5vyd5hrnmczz12-6542c344bcf0077e7530a0e8f02034aa92b52b39.tar.gz/pkgs/applications/science/logic/saw-tools/default.nix:55","date":"2015-08-08"}],"platforms":["i686-linux","x86_64-linux","armv5tel-linux","armv6l-linux","armv7l-linux","mips64el-linux"]}}