{"frozen":{"name":"unvanquished","shortDescription":"A FLOSS FPS combining RTS elements with a futuristic, sci-fi setting.","longDescription":"Unvanquished is a free, open-source first-person shooter\ncombining real-time strategy elements with a futuristic, sci-fi\nsetting. It is available for Windows, Linux, and Mac OS X.\n\nFeatures:\n\n* Two teams\n  Play as either the technologically advanced humans or the highly\n  adaptable aliens, with a fresh gameplay experience on both\n  sides.\n\n* Build a base\n  Construct and maintain your base with a variety of useful\n  structures, or group up with teammates to take on the other\n  team.\n\n* Level up\n  Earn rewards for victories against the other team, whether it's\n  a deadly new weapon or access to a whole new alien form.\n\n* Customize\n  Compatibility with Quake 3 file formats and modification tools\n  allows for extensive customization of the game and its\n  setting.\n","versionString":"0.13.1","homepage":"http://unvanquished.net","versionNumberList":[0,13,1]},"flexible":{"sources":[{"git":"https://github.com/NixOS/nixpkgs.git","commit":"ad4156e4973abe0c306617c033169bc9c6fa44e1","attributePath":["unvanquished"],"position":null,"date":"2013-09-20"}]}}