{"frozen":{"name":"tzupdate","shortDescription":"Update timezone information based on geoip.","versionString":"1.3.1","homepage":"https://github.com/cdown/tzupdate","license":{"fullName":"The Unlicense","shortName":"unlicense","spdxId":"Unlicense","url":"http://spdx.org/licenses/Unlicense.html"},"versionNumberList":[1,3,1]},"flexible":{"sources":[{"git":"https://github.com/NixOS/nixpkgs.git","commit":"22091c912a38f2f9f8cb8efd612915a9346e57cb","attributePath":["tzupdate"],"position":"/nix/store/z9pm444cj6kmm2m01vf28xa94bakm7cm-22091c912a38f2f9f8cb8efd612915a9346e57cb.tar.gz/pkgs/applications/misc/tzupdate/default.nix:18","date":"2019-03-01"}],"platforms":[{}]}}