{"frozen":{"name":"hubstaff","shortDescription":"Time tracking software","versionString":"1.6.2-328c666b","homepage":"https://hubstaff.com/","license":{"deprecated":false,"free":false,"fullName":"Unfree","redistributable":false,"shortName":"unfree"},"versionNumberList":[1,6,2,"-328c666b"]},"flexible":{"unfree":true,"insecure":false,"broken":false,"sources":[{"git":"https://github.com/NixOS/nixpkgs.git","commit":"273bcc7a9a6bcf22781c7fb61df01ae8a7c68ec9","attributePath":["hubstaff"],"position":"/nix/store/wl7qj93w4x4z82izkg41gfxr2y2dw9n1-273bcc7a9a6bcf22781c7fb61df01ae8a7c68ec9.tar.gz/pkgs/applications/misc/hubstaff/default.nix:71","date":"2021-10-20"}],"platforms":["x86_64-linux"]}}