{"frozen":{"name":"ocserv","shortDescription":"This program is openconnect VPN server (ocserv), a server for the openconnect VPN client","versionString":"0.12.6","homepage":"https://gitlab.com/openconnect/ocserv","license":{"deprecated":true,"free":true,"fullName":"GNU General Public License v2.0","redistributable":true,"shortName":"gpl2","spdxId":"GPL-2.0","url":"https://spdx.org/licenses/GPL-2.0.html"},"versionNumberList":[0,12,6]},"flexible":{"unfree":false,"insecure":false,"broken":false,"sources":[{"git":"https://github.com/NixOS/nixpkgs.git","commit":"273bcc7a9a6bcf22781c7fb61df01ae8a7c68ec9","attributePath":["ocserv"],"position":"/nix/store/wl7qj93w4x4z82izkg41gfxr2y2dw9n1-273bcc7a9a6bcf22781c7fb61df01ae8a7c68ec9.tar.gz/pkgs/tools/networking/ocserv/default.nix:23","date":"2021-10-20"}]}}