{"frozen":{"name":"lablgtkmathview","shortDescription":"OCaml bindings for gtkmathview","versionString":"0.7.2","homepage":"http://helm.cs.unibo.it/mml-widget/","license":{"fullName":"GNU Library General Public License v2 or later","shortName":"lgpl2Plus","spdxId":"LGPL-2.0-or-later","url":"https://spdx.org/licenses/LGPL-2.0-or-later.html"},"versionNumberList":[0,7,2]},"flexible":{"broken":true,"sources":[{"git":"https://github.com/NixOS/nixpkgs.git","commit":"05a7b69509f78b4ae9d04fcdf8f57ceb435572fc","attributePath":["ocamlPackages","lablgtkmathview"],"position":"/nix/store/7l0a51yav8p04d9l8dd5pmhds7pqvalf-05a7b69509f78b4ae9d04fcdf8f57ceb435572fc.tar.gz/pkgs/development/ocaml-modules/lablgtkmathview/default.nix:35","date":"2020-05-05"}]}}