{"frozen":{"name":"cinnamon-session","shortDescription":"The cinnamon session files","versionString":"2.0.6","homepage":"http://cinnamon.linuxmint.com","versionNumberList":[2,0,6]},"flexible":{"broken":true,"sources":[{"git":"https://github.com/NixOS/nixpkgs.git","commit":"6542c344bcf0077e7530a0e8f02034aa92b52b39","attributePath":["cinnamon","cinnamon-session"],"position":"/nix/store/f9gnvpp942xsz6y4wk5vyd5hrnmczz12-6542c344bcf0077e7530a0e8f02034aa92b52b39.tar.gz/pkgs/desktops/cinnamon/cinnamon-session.nix:42","date":"2015-08-08"}],"platforms":["i686-linux","x86_64-linux","armv5tel-linux","armv6l-linux","armv7l-linux","mips64el-linux"]}}