{"frozen":{"name":"inkscape","longDescription":"Inkscape is a feature-rich vector graphics editor that edits\nfiles in the W3C SVG (Scalable Vector Graphics) file format.\n\nIf you want to import .eps files install ps2edit.\n","versionString":"0.48.4","homepage":"http://www.inkscape.org","license":"GPL","versionNumberList":[0,48,4]},"flexible":{"sources":[{"git":"https://github.com/NixOS/nixpkgs.git","commit":"ad4156e4973abe0c306617c033169bc9c6fa44e1","attributePath":["inkscape"],"position":null,"date":"2013-09-20"}]}}