{"frozen":{"name":"rebar","shortDescription":"Erlang build tool that makes it easy to compile and test Erlang applications, port drivers and releases.","longDescription":"rebar is a self-contained Erlang script, so it's easy to\ndistribute or even embed directly in a project. Where possible,\nrebar uses standard Erlang/OTP conventions for project\nstructures, thus minimizing the amount of build configuration\nwork. rebar also provides dependency management, enabling\napplication writers to easily re-use common libraries from a\nvariety of locations (git, hg, etc).\n","versionString":"2.1.0-pre","homepage":"https://github.com/rebar/rebar","versionNumberList":[2,1,0,"-pre"]},"flexible":{"sources":[{"git":"https://github.com/NixOS/nixpkgs.git","commit":"ad4156e4973abe0c306617c033169bc9c6fa44e1","attributePath":["rebar"],"position":null,"date":"2013-09-20"}],"platforms":["i686-linux","x86_64-linux","powerpc-linux","armv5tel-linux","armv7l-linux","mips64el-linux"]}}