{"frozen":{"name":"x86info","shortDescription":"Identification utility for the x86 series of processors","longDescription":"x86info will identify all Intel/AMD/Centaur/Cyrix/VIA CPUs. It leverages\nthe cpuid kernel module where possible.  it supports parsing model specific\nregisters (MSRs) via the msr kernel module.  it will approximate processor\nfrequency, and identify the cache sizes and layout. \n","versionString":"1.30","homepage":"http://codemonkey.org.uk/projects/x86info/","license":{"fullName":"GNU General Public License v2.0 only","shortName":"gpl2","spdxId":"GPL-2.0-only","url":"http://spdx.org/licenses/GPL-2.0-only.html"},"versionNumberList":[1,30]},"flexible":{"sources":[{"git":"https://github.com/NixOS/nixpkgs.git","commit":"22091c912a38f2f9f8cb8efd612915a9346e57cb","attributePath":["x86info"],"position":"/nix/store/z9pm444cj6kmm2m01vf28xa94bakm7cm-22091c912a38f2f9f8cb8efd612915a9346e57cb.tar.gz/pkgs/os-specific/linux/x86info/default.nix:27","date":"2019-03-01"}],"platforms":["i686-linux","x86_64-linux"]}}