{"frozen":{"name":"python2.7-Django","shortDescription":"A high-level Python Web framework","versionString":"1.8.19","homepage":"https://www.djangoproject.com/","license":{"fullName":"BSD Zero Clause License","shortName":"bsd0","spdxId":"0BSD","url":"http://spdx.org/licenses/0BSD.html"},"versionNumberList":[1,8,19]},"flexible":{"sources":[{"git":"https://github.com/NixOS/nixpkgs.git","commit":"22091c912a38f2f9f8cb8efd612915a9346e57cb","attributePath":["python27Packages","django_1_8"],"position":"/nix/store/z9pm444cj6kmm2m01vf28xa94bakm7cm-22091c912a38f2f9f8cb8efd612915a9346e57cb.tar.gz/pkgs/development/python-modules/django/1_8.nix:25","date":"2019-03-01"}],"platforms":[{}]}}