{"frozen":{"name":"vscode-extension-WakaTime-vscode-wakatime","shortDescription":"Visual Studio Code plugin for automatic time tracking and metrics generated\nfrom your programming activity\n","versionString":"17.1.0","license":{"deprecated":false,"free":true,"fullName":"BSD 3-clause \"New\" or \"Revised\" License","redistributable":true,"shortName":"bsd3","spdxId":"BSD-3-Clause","url":"https://spdx.org/licenses/BSD-3-Clause.html"},"versionNumberList":[17,1,0]},"flexible":{"unfree":false,"insecure":false,"broken":false,"sources":[{"git":"https://github.com/NixOS/nixpkgs.git","commit":"1097381d400990a3c9e4732a1a180e71ace9edcc","attributePath":["vscode-extensions","WakaTime","vscode-wakatime"],"position":"/nix/store/gqn35g78jqsq87nmdkx9vbhqk3mjd813-1097381d400990a3c9e4732a1a180e71ace9edcc.tar.gz/pkgs/misc/vscode-extensions/wakatime/default.nix:16","date":"2022-01-31"}]}}