{"frozen":{"name":"ruby-rmail","shortDescription":"A MIME mail parsing and generation library.","longDescription":"RMail is a lightweight mail library containing various utility classes and modules that allow ruby scripts to parse, modify, and generate MIME mail messages.","versionString":"1.0.0","homepage":"http://www.rfc20.org/rubymail","versionNumberList":[1,0,0]},"flexible":{"sources":[{"git":"https://github.com/NixOS/nixpkgs.git","commit":"ad4156e4973abe0c306617c033169bc9c6fa44e1","attributePath":["rubyLibs","rmail"],"position":null,"date":"2013-09-20"}]}}