{"frozen":{"name":"python2.7-pygmo","shortDescription":"Parallel optimisation for Python","versionString":"2.9","homepage":"https://esa.github.io/pagmo2/","license":{"fullName":"GNU General Public License v3.0 or later","shortName":"gpl3Plus","spdxId":"GPL-3.0-or-later","url":"http://spdx.org/licenses/GPL-3.0-or-later.html"},"versionNumberList":[2,9]},"flexible":{"sources":[{"git":"https://github.com/NixOS/nixpkgs.git","commit":"22091c912a38f2f9f8cb8efd612915a9346e57cb","attributePath":["python27Packages","pygmo"],"position":"/nix/store/z9pm444cj6kmm2m01vf28xa94bakm7cm-22091c912a38f2f9f8cb8efd612915a9346e57cb.tar.gz/pkgs/development/python-modules/pygmo/default.nix:48","date":"2019-03-01"}],"platforms":[{}]}}