{"frozen":{"name":"python2.7-boto","shortDescription":"Python interface to Amazon Web Services","longDescription":"The boto module is an integrated interface to current and\nfuture infrastructural services offered by Amazon Web\nServices.  This includes S3, SQS, EC2, among others.\n","versionString":"2.49.0","homepage":"https://github.com/boto/boto","license":{"fullName":"MIT License","shortName":"mit","spdxId":"MIT","url":"http://spdx.org/licenses/MIT.html"},"versionNumberList":[2,49,0]},"flexible":{"sources":[{"git":"https://github.com/NixOS/nixpkgs.git","commit":"22091c912a38f2f9f8cb8efd612915a9346e57cb","attributePath":["python27Packages","boto"],"position":"/nix/store/z9pm444cj6kmm2m01vf28xa94bakm7cm-22091c912a38f2f9f8cb8efd612915a9346e57cb.tar.gz/pkgs/development/python-modules/boto/default.nix:30","date":"2019-03-01"}],"platforms":[{}]}}