{"frozen":{"name":"conky","shortDescription":"Advanced, highly configurable system monitor based on torsmo","versionString":"1.9.0","homepage":"http://conky.sourceforge.net/","license":{"fullName":"GNU General Public License v3.0 or later","shortName":"gpl3Plus","spdxId":"GPL-3.0+","url":"http://spdx.org/licenses/GPL-3.0+"},"versionNumberList":[1,9,0]},"flexible":{"sources":[{"git":"https://github.com/NixOS/nixpkgs.git","commit":"6542c344bcf0077e7530a0e8f02034aa92b52b39","attributePath":["conky"],"position":"/nix/store/f9gnvpp942xsz6y4wk5vyd5hrnmczz12-6542c344bcf0077e7530a0e8f02034aa92b52b39.tar.gz/pkgs/os-specific/linux/conky/default.nix:115","date":"2015-08-08"}]}}