{"frozen":{"name":"pcsx2-unstable","shortDescription":"Playstation 2 emulator","longDescription":"PCSX2 is an open-source PlayStation 2 (AKA PS2) emulator. Its purpose\nis to emulate the PS2 hardware, using a combination of MIPS CPU\nInterpreters, Recompilers and a Virtual Machine which manages hardware\nstates and PS2 system memory. This allows you to play PS2 games on your\nPC, with many additional features and benefits.\n","versionString":"2020-11-13","homepage":"https://pcsx2.net","license":{"deprecated":false,"free":true,"fullName":"Unspecified free software license","redistributable":true,"shortName":"free"},"versionNumberList":[]},"flexible":{"unfree":false,"insecure":false,"broken":false,"sources":[{"git":"https://github.com/NixOS/nixpkgs.git","commit":"273bcc7a9a6bcf22781c7fb61df01ae8a7c68ec9","attributePath":["pcsx2"],"position":"/nix/store/wl7qj93w4x4z82izkg41gfxr2y2dw9n1-273bcc7a9a6bcf22781c7fb61df01ae8a7c68ec9.tar.gz/pkgs/misc/emulators/pcsx2/default.nix:95","date":"2021-10-20"}],"platforms":["i686-cygwin","x86_64-cygwin","x86_64-darwin","i686-darwin","i686-freebsd","x86_64-freebsd","i686-genode","x86_64-genode","x86_64-solaris","i686-linux","x86_64-linux","i686-netbsd","x86_64-netbsd","i686-none","x86_64-none","i686-openbsd","x86_64-openbsd","x86_64-redox","x86_64-windows","i686-windows"]}}