{"frozen":{"name":"python2.7-fdint","shortDescription":"A free, open-source python package for quickly and precisely approximating Fermi-Dirac integrals","versionString":"2.0.2","homepage":"https://github.com/scott-maddox/fdint","license":{"fullName":"MIT License","shortName":"mit","spdxId":"MIT","url":"http://spdx.org/licenses/MIT.html"},"versionNumberList":[2,0,2]},"flexible":{"sources":[{"git":"https://github.com/NixOS/nixpkgs.git","commit":"22091c912a38f2f9f8cb8efd612915a9346e57cb","attributePath":["python27Packages","fdint"],"position":"/nix/store/z9pm444cj6kmm2m01vf28xa94bakm7cm-22091c912a38f2f9f8cb8efd612915a9346e57cb.tar.gz/pkgs/development/python-modules/fdint/default.nix:32","date":"2019-03-01"}],"platforms":[{}]}}