{"frozen":{"name":"asn1c","shortDescription":"Open Source ASN.1 Compiler","versionString":"0.9.28","homepage":"http://lionet.info/asn1c/compiler.html","license":{"fullName":"BSD 2-clause \"Simplified\" License","shortName":"bsd2","spdxId":"BSD-2-Clause","url":"http://spdx.org/licenses/BSD-2-Clause.html"},"versionNumberList":[0,9,28]},"flexible":{"sources":[{"git":"https://github.com/NixOS/nixpkgs.git","commit":"22091c912a38f2f9f8cb8efd612915a9346e57cb","attributePath":["asn1c"],"position":"/nix/store/z9pm444cj6kmm2m01vf28xa94bakm7cm-22091c912a38f2f9f8cb8efd612915a9346e57cb.tar.gz/pkgs/development/compilers/asn1c/default.nix:28","date":"2019-03-01"}],"platforms":[{}]}}