{"frozen":{"name":"rime-data","shortDescription":"Schema data of Rime Input Method Engine","longDescription":"Rime-data provides schema data for Rime Input Method Engine.\n","versionString":"0.38.20211002","homepage":"https://rime.im","license":[{"deprecated":false,"free":true,"fullName":"GNU General Public License v3.0 only","redistributable":true,"shortName":"gpl3Only","spdxId":"GPL-3.0-only","url":"https://spdx.org/licenses/GPL-3.0-only.html"},{"deprecated":false,"free":true,"fullName":"GNU Lesser General Public License v3.0 only","redistributable":true,"shortName":"lgpl3Only","spdxId":"LGPL-3.0-only","url":"https://spdx.org/licenses/LGPL-3.0-only.html"},{"deprecated":false,"free":true,"fullName":"Apache License 2.0","redistributable":true,"shortName":"asl20","spdxId":"Apache-2.0","url":"https://spdx.org/licenses/Apache-2.0.html"},{"deprecated":false,"free":true,"fullName":"Creative Commons Attribution 4.0","redistributable":true,"shortName":"cc-by-40","spdxId":"CC-BY-4.0","url":"https://spdx.org/licenses/CC-BY-4.0.html"}],"versionNumberList":[0,38,20211002]},"flexible":{"unfree":false,"insecure":false,"broken":false,"sources":[{"git":"https://github.com/NixOS/nixpkgs.git","commit":"1097381d400990a3c9e4732a1a180e71ace9edcc","attributePath":["rime-data"],"position":"/nix/store/gqn35g78jqsq87nmdkx9vbhqk3mjd813-1097381d400990a3c9e4732a1a180e71ace9edcc.tar.gz/pkgs/data/misc/rime-data/default.nix:27","date":"2022-01-31"}]}}