{"frozen":{"name":"molden","shortDescription":"Display and manipulate molecular structures","versionString":"5.9.3","homepage":"http://www.cmbi.ru.nl/molden/","license":{"free":false,"fullName":"Free for academic/non-profit use","url":"http://www.cmbi.ru.nl/molden/CopyRight.html"},"versionNumberList":[5,9,3]},"flexible":{"sources":[{"git":"https://github.com/NixOS/nixpkgs.git","commit":"22091c912a38f2f9f8cb8efd612915a9346e57cb","attributePath":["molden"],"position":"/nix/store/z9pm444cj6kmm2m01vf28xa94bakm7cm-22091c912a38f2f9f8cb8efd612915a9346e57cb.tar.gz/pkgs/applications/science/chemistry/molden/default.nix:33","date":"2019-03-01"}],"platforms":[{"kernel":{"_type":"kernel","execFormat":{"_type":"exec-format","name":"elf"},"families":{},"name":"linux"}}]}}