{"frozen":{"name":"pkcs11-helper","shortDescription":"Library that simplifies the interaction with PKCS#11 providers","versionString":"20121123-5d412bad60","homepage":"https://www.opensc-project.org/opensc/wiki/pkcs11-helper","license":["BSD",{"fullName":"GNU General Public License v2.0 only","shortName":"gpl2","spdxId":"GPL-2.0","url":"http://spdx.org/licenses/GPL-2.0"}],"versionNumberList":[]},"flexible":{"sources":[{"git":"https://github.com/NixOS/nixpkgs.git","commit":"6542c344bcf0077e7530a0e8f02034aa92b52b39","attributePath":["pkcs11helper"],"position":"/nix/store/f9gnvpp942xsz6y4wk5vyd5hrnmczz12-6542c344bcf0077e7530a0e8f02034aa92b52b39.tar.gz/pkgs/development/libraries/pkcs11helper/default.nix:22","date":"2015-08-08"}]}}