{"frozen":{"name":"opencc","shortDescription":"A project for conversion between Traditional and Simplified Chinese","longDescription":"Open Chinese Convert (OpenCC) is an opensource project for conversion between\nTraditional Chinese and Simplified Chinese, supporting character-level conversion,\nphrase-level conversion, variant conversion and regional idioms among Mainland China,\nTaiwan and Hong kong.\n","versionString":"1.0.5","homepage":"https://github.com/BYVoid/OpenCC","license":{"fullName":"Apache License 2.0","shortName":"asl20","spdxId":"Apache-2.0","url":"http://spdx.org/licenses/Apache-2.0.html"},"versionNumberList":[1,0,5]},"flexible":{"sources":[{"git":"https://github.com/NixOS/nixpkgs.git","commit":"22091c912a38f2f9f8cb8efd612915a9346e57cb","attributePath":["opencc"],"position":"/nix/store/z9pm444cj6kmm2m01vf28xa94bakm7cm-22091c912a38f2f9f8cb8efd612915a9346e57cb.tar.gz/pkgs/tools/text/opencc/default.nix:23","date":"2019-03-01"}],"platforms":[{"kernel":{"_type":"kernel","execFormat":{"_type":"exec-format","name":"elf"},"families":{},"name":"linux"}}]}}