{"frozen":{"name":"lzip","shortDescription":"a lossless data compressor based on the LZMA algorithm","versionString":"1.14","homepage":"http://www.nongnu.org/lzip/lzip.html","license":{"fullName":"GNU General Public License version 3 or later","shortName":"GPLv3+","url":"http://www.fsf.org/licensing/licenses/gpl.html"},"versionNumberList":[1,14]},"flexible":{"sources":[{"git":"https://github.com/NixOS/nixpkgs.git","commit":"ad4156e4973abe0c306617c033169bc9c6fa44e1","attributePath":["lzip"],"position":null,"date":"2013-09-20"}],"platforms":["i686-linux","x86_64-linux","powerpc-linux","armv5tel-linux","armv7l-linux","mips64el-linux","x86_64-darwin","i686-freebsd","x86_64-freebsd","powerpc-freebsd","i686-openbsd","x86_64-openbsd"]}}