{"frozen":{"name":"python2.7-ptest","shortDescription":"Test classes and test cases using decorators, execute test cases by command line, and get clear reports","versionString":"1.7.4","homepage":"https://pypi.python.org/pypi/ptest","license":{"fullName":"Apache License 2.0","shortName":"asl20","spdxId":"Apache-2.0","url":"http://spdx.org/licenses/Apache-2.0.html"},"versionNumberList":[1,7,4]},"flexible":{"sources":[{"git":"https://github.com/NixOS/nixpkgs.git","commit":"22091c912a38f2f9f8cb8efd612915a9346e57cb","attributePath":["python27Packages","ptest"],"position":"/nix/store/z9pm444cj6kmm2m01vf28xa94bakm7cm-22091c912a38f2f9f8cb8efd612915a9346e57cb.tar.gz/pkgs/development/python-modules/ptest/default.nix:18","date":"2019-03-01"}],"platforms":[{}]}}