{"frozen":{"name":"alda","shortDescription":"A music programming language for musicians","versionString":"2.0.6","homepage":"https://alda.io","license":{"deprecated":false,"free":true,"fullName":"Eclipse Public License 1.0","redistributable":true,"shortName":"epl10","spdxId":"EPL-1.0","url":"https://spdx.org/licenses/EPL-1.0.html"},"versionNumberList":[2,0,6]},"flexible":{"unfree":false,"insecure":false,"broken":false,"sources":[{"git":"https://github.com/NixOS/nixpkgs.git","commit":"1097381d400990a3c9e4732a1a180e71ace9edcc","attributePath":["alda"],"position":"/nix/store/gqn35g78jqsq87nmdkx9vbhqk3mjd813-1097381d400990a3c9e4732a1a180e71ace9edcc.tar.gz/pkgs/development/interpreters/alda/default.nix:34","date":"2022-01-31"}],"platforms":["i686-linux","x86_64-linux","aarch64-linux","armv7l-linux","armv6l-linux"]}}