{"frozen":{"name":"partclone","shortDescription":"Utilities to save and restore used blocks on a partition","longDescription":"Partclone provides utilities to save and restore used blocks on a\npartition and is designed for higher compatibility of the file system by\nusing existing libraries, e.g. e2fslibs is used to read and write the\next2 partition.\n","versionString":"0.3.11","homepage":"https://partclone.org","license":{"fullName":"GNU General Public License v2.0 only","shortName":"gpl2","spdxId":"GPL-2.0-only","url":"http://spdx.org/licenses/GPL-2.0-only.html"},"versionNumberList":[0,3,11]},"flexible":{"sources":[{"git":"https://github.com/NixOS/nixpkgs.git","commit":"22091c912a38f2f9f8cb8efd612915a9346e57cb","attributePath":["partclone"],"position":"/nix/store/z9pm444cj6kmm2m01vf28xa94bakm7cm-22091c912a38f2f9f8cb8efd612915a9346e57cb.tar.gz/pkgs/tools/backup/partclone/default.nix:38","date":"2019-03-01"}],"platforms":[{"kernel":{"_type":"kernel","execFormat":{"_type":"exec-format","name":"elf"},"families":{},"name":"linux"}}]}}