{"frozen":{"name":"ldc","shortDescription":"The LLVM-based D compiler","versionString":"1.14.0","homepage":"https://github.com/ldc-developers/ldc","license":[{"fullName":"BSD 3-clause \"New\" or \"Revised\" License","shortName":"bsd3","spdxId":"BSD-3-Clause","url":"http://spdx.org/licenses/BSD-3-Clause.html"},{"fullName":"Boost Software License 1.0","shortName":"boost","spdxId":"BSL-1.0","url":"http://spdx.org/licenses/BSL-1.0.html"},{"fullName":"MIT License","shortName":"mit","spdxId":"MIT","url":"http://spdx.org/licenses/MIT.html"},{"fullName":"University of Illinois/NCSA Open Source License","shortName":"ncsa","spdxId":"NCSA","url":"http://spdx.org/licenses/NCSA.html"},{"fullName":"GNU General Public License v2.0 or later","shortName":"gpl2Plus","spdxId":"GPL-2.0-or-later","url":"http://spdx.org/licenses/GPL-2.0-or-later.html"}],"versionNumberList":[1,14,0]},"flexible":{"sources":[{"git":"https://github.com/NixOS/nixpkgs.git","commit":"22091c912a38f2f9f8cb8efd612915a9346e57cb","attributePath":["ldc"],"position":"/nix/store/z9pm444cj6kmm2m01vf28xa94bakm7cm-22091c912a38f2f9f8cb8efd612915a9346e57cb.tar.gz/pkgs/development/compilers/ldc/default.nix:165","date":"2019-03-01"}],"platforms":["x86_64-linux","i686-linux","x86_64-darwin"]}}