{"frozen":{"name":"python3.7-bottle","shortDescription":"A fast and simple micro-framework for small web-applications","versionString":"0.12.16","homepage":"http://bottlepy.org","license":{"fullName":"MIT License","shortName":"mit","spdxId":"MIT","url":"http://spdx.org/licenses/MIT.html"},"versionNumberList":[0,12,16]},"flexible":{"sources":[{"git":"https://github.com/NixOS/nixpkgs.git","commit":"22091c912a38f2f9f8cb8efd612915a9346e57cb","attributePath":["python37Packages","bottle"],"position":"/nix/store/z9pm444cj6kmm2m01vf28xa94bakm7cm-22091c912a38f2f9f8cb8efd612915a9346e57cb.tar.gz/pkgs/development/python-modules/bottle/default.nix:16","date":"2019-03-01"}],"platforms":[{}]}}